kk_flow/__init__.py
kk_flow/mm/__init__.py
kk_flow/mm/core.py
kk_flow/utils/__init__.py
kk_flow/utils/utils.py
luotianhang_kaikeba_flow-0.0.1.dist-info/LICENSE
luotianhang_kaikeba_flow-0.0.1.dist-info/METADATA
luotianhang_kaikeba_flow-0.0.1.dist-info/WHEEL
luotianhang_kaikeba_flow-0.0.1.dist-info/top_level.txt
luotianhang_kaikeba_flow-0.0.1.dist-info/RECORD
