Metadata-Version: 2.1
Name: luotianhang-kaikeba-flow
Version: 0.0.1
Summary: this is a test
Home-page: UNKNOWN
Author: luotianhang
Author-email: 673567903@qq.com
License: UNKNOWN
Platform: UNKNOWN
Classifier: Programming Language :: Python :: 3
Classifier: License :: OSI Approved :: MIT License
Classifier: Operating System :: OS Independent
Requires-Python: >=3.6
